matty.py
matty-0.9.0.dist-info/METADATA
matty-0.9.0.dist-info/WHEEL
matty-0.9.0.dist-info/entry_points.txt
matty-0.9.0.dist-info/RECORD
