Metadata-Version: 2.4
Name: matty
Version: 0.9.0
Summary: A Terminal UI for Matrix chat - simple and AI-friendly
Project-URL: Homepage, https://github.com/basnijholt/matty
Project-URL: Documentation, https://github.com/basnijholt/matty#readme
Project-URL: Repository, https://github.com/basnijholt/matty
Project-URL: Issues, https://github.com/basnijholt/matty/issues
Author-email: Bas Nijholt <bas@nijho.lt>
License: MIT
Keywords: ai-friendly,chat,cli,client,matrix
Classifier: Development Status :: 4 - Beta
Classifier: Environment :: Console
Classifier: Intended Audience :: Developers
Classifier: License :: OSI Approved :: MIT License
Classifier: Programming Language :: Python :: 3
Classifier: Programming Language :: Python :: 3.12
Classifier: Topic :: Communications :: Chat
Classifier: Topic :: Software Development :: Libraries :: Python Modules
Requires-Python: >=3.12
Requires-Dist: aiofiles>=24.1.0
Requires-Dist: matrix-nio>=0.25.2
Requires-Dist: pydantic-settings>=2.10.1
Requires-Dist: pydantic>=2.11.7
Requires-Dist: python-dotenv>=1.1.1
Requires-Dist: rich>=13.0.0
Requires-Dist: typer>=0.16.1
